LICENSE
MANIFEST.in
README.rst
setup.py
Flask_Avatar.egg-info/PKG-INFO
Flask_Avatar.egg-info/SOURCES.txt
Flask_Avatar.egg-info/dependency_links.txt
Flask_Avatar.egg-info/not-zip-safe
Flask_Avatar.egg-info/requires.txt
Flask_Avatar.egg-info/top_level.txt
flask_avatar/__init__.py
flask_avatar/avatar.py
flask_avatar/data/wqy-microhei.ttc