Metadata-Version: 1.1
Name: Flask-Avatar
Version: 0.1.3
Summary: To generate avatar for flask
Home-page: https://github.com/honmaple/flask-avatar
Author: honmaple
Author-email: xiyang0807@gmail.com
License: BSD
Platform: any
Classifier: Environment :: Web Environment
Classifier: Intended Audience :: Developers
Classifier: License :: OSI Approved :: BSD License
Classifier: Operating System :: OS Independent
Classifier: Programming Language :: Python
Classifier: Topic :: Internet :: WWW/HTTP :: Dynamic Content
Classifier: Topic :: Software Development :: Libraries :: Python Modules
